README.md
extended_stenotype.py
setup.cfg
setup.py
plover_stenotype_extended.egg-info/PKG-INFO
plover_stenotype_extended.egg-info/SOURCES.txt
plover_stenotype_extended.egg-info/dependency_links.txt
plover_stenotype_extended.egg-info/entry_points.txt
plover_stenotype_extended.egg-info/requires.txt
plover_stenotype_extended.egg-info/top_level.txt
plover_stenotype_extended.egg-info/zip-safe