Metadata-Version: 2.1
Name: plover-stenotype-extended
Version: 1.0.0
Summary: Plover Stenotype layout but with extra keys
Home-page: https://github.com/sammdot/plover-stenotype-extended
License: UNKNOWN
Keywords: plover plover_plugin
Platform: UNKNOWN
Classifier: Programming Language :: Python :: 3.6
Classifier: Programming Language :: Python :: 3.7
Classifier: Programming Language :: Python :: 3.8
Classifier: Programming Language :: Python :: 3.9
